[ {
  "fee_amount" : 1000.0,
  "is_active" : true,
  "category_id" : 1,
  "month_id" : 13,
  "class_id" : 1,
  "session_id" : 1,
  "class_wise_fee_id" : 1
}, {
  "fee_amount" : 10000.0,
  "is_active" : true,
  "category_id" : 6,
  "month_id" : 1,
  "class_id" : 1,
  "session_id" : 1,
  "class_wise_fee_id" : 2
}, {
  "fee_amount" : 100.0,
  "is_active" : true,
  "category_id" : 1,
  "month_id" : 13,
  "class_id" : 17,
  "session_id" : 1,
  "class_wise_fee_id" : 3
}, {
  "fee_amount" : 10000.0,
  "is_active" : true,
  "category_id" : 6,
  "month_id" : 1,
  "class_id" : 17,
  "session_id" : 1,
  "class_wise_fee_id" : 4
}, {
  "fee_amount" : 5000.0,
  "is_active" : true,
  "category_id" : 5,
  "month_id" : 1,
  "class_id" : 1,
  "session_id" : 1,
  "class_wise_fee_id" : 5
} ]